cgc/__init__.py
cgc/__version__.py
cgc/cgc.py
cgc/coclustering.py
cgc/coclustering_dask.py
cgc/coclustering_numpy.py
cgc/kmeans.py
cgc/results.py
cgc/triclustering.py
cgc/triclustering_dask.py
cgc/triclustering_numpy.py
cgc/utils.py
clustering_geodata_cubes-0.8.0.dist-info/LICENSE
clustering_geodata_cubes-0.8.0.dist-info/METADATA
clustering_geodata_cubes-0.8.0.dist-info/NOTICE
clustering_geodata_cubes-0.8.0.dist-info/WHEEL
clustering_geodata_cubes-0.8.0.dist-info/top_level.txt
clustering_geodata_cubes-0.8.0.dist-info/RECORD
