Metadata-Version: 2.1
Name: clustering-geodata-cubes
Version: 0.8.0
Summary: CGC: a Scalable Python Package for Co- and Tri-Clustering of Geodata Cubes
Author: Ou Ku, Meiert W. Grootes, Emma Izquierdo-Verdiguier, Serkan Girgin, Raul Zurita-Milla
Author-email: Francesco Nattino <f.nattino@esciencecenter.nl>
License: 
Project-URL: repository, https://github.com/phenology/cgc
Project-URL: documentation, https://cgc.readthedocs.io
Project-URL: changelog, https://github.com/phenology/cgc/blob/master/CHANGELOG.rst
Project-URL: doi, https://doi.org/10.5281/zenodo.3979172
Keywords: clustering,co-clustering,tri-clustering,earth observation,distributed computing
Classifier: Development Status :: 2 - Pre-Alpha
Classifier: Intended Audience :: Developers
Classifier: License :: OSI Approved :: Apache Software License
Classifier: Natural Language :: English
Classifier: Programming Language :: Python :: 3
Classifier: Programming Language :: Python :: 3.7
Classifier: Programming Language :: Python :: 3.8
Classifier: Programming Language :: Python :: 3.9
License-File: LICENSE
License-File: NOTICE
Requires-Dist: dask[complete]
Requires-Dist: matplotlib
Requires-Dist: numba
Requires-Dist: numpy
Requires-Dist: scikit-learn
Provides-Extra: dev
Requires-Dist: pytest (>=6.0) ; extra == 'dev'
Requires-Dist: pytest-cov ; extra == 'dev'
Requires-Dist: pycodestyle ; extra == 'dev'
Provides-Extra: docs
Requires-Dist: sphinx ; extra == 'docs'
Requires-Dist: docutils (==0.16) ; extra == 'docs'
Requires-Dist: sphinx-rtd-theme (==0.5.2) ; extra == 'docs'
Requires-Dist: recommonmark ; extra == 'docs'
